{
  "model_type": "RandomForestClassifier",
  "n_estimators": 100,
  "max_depth": 15,
  "n_features": 28,
  "feature_names": [
    "pct_digits",
    "pct_alpha",
    "pct_spaces",
    "pct_special",
    "avg_length",
    "std_length",
    "min_length",
    "max_length",
    "unique_ratio",
    "null_rate",
    "has_leading_zeros",
    "has_decimal_point",
    "has_dash",
    "has_slash",
    "has_colon",
    "has_at_sign",
    "has_comma",
    "pct_match_int",
    "pct_match_float",
    "pct_match_date",
    "pct_match_email",
    "pct_match_url",
    "pct_match_phone",
    "pct_match_uuid",
    "pct_match_bool",
    "pct_match_currency",
    "pct_match_percentage",
    "pct_match_zip"
  ],
  "classes": [
    "boolean",
    "category",
    "currency",
    "date",
    "datetime",
    "email",
    "float",
    "integer",
    "percentage",
    "phone",
    "text",
    "url",
    "uuid",
    "zip_code"
  ],
  "n_classes": 14,
  "training_samples": 112000,
  "test_samples": 28000,
  "accuracy": 1.0,
  "per_class_f1": {
    "boolean": 1.0,
    "category": 1.0,
    "currency": 1.0,
    "date": 1.0,
    "datetime": 1.0,
    "email": 1.0,
    "float": 1.0,
    "integer": 1.0,
    "percentage": 1.0,
    "phone": 1.0,
    "text": 1.0,
    "url": 1.0,
    "uuid": 1.0,
    "zip_code": 1.0
  },
  "feature_importances": {
    "pct_digits": 0.0532,
    "pct_alpha": 0.0406,
    "pct_spaces": 0.0166,
    "pct_special": 0.0606,
    "avg_length": 0.1018,
    "std_length": 0.0427,
    "min_length": 0.0118,
    "max_length": 0.0798,
    "unique_ratio": 0.0548,
    "null_rate": 0.0,
    "has_leading_zeros": 0.0107,
    "has_decimal_point": 0.0482,
    "has_dash": 0.0148,
    "has_slash": 0.0095,
    "has_colon": 0.0459,
    "has_at_sign": 0.0259,
    "has_comma": 0.0155,
    "pct_match_int": 0.0333,
    "pct_match_float": 0.0421,
    "pct_match_date": 0.0566,
    "pct_match_email": 0.0232,
    "pct_match_url": 0.0193,
    "pct_match_phone": 0.0247,
    "pct_match_uuid": 0.0258,
    "pct_match_bool": 0.0445,
    "pct_match_currency": 0.0367,
    "pct_match_percentage": 0.0277,
    "pct_match_zip": 0.0336
  },
  "training_time_seconds": 2.5,
  "total_time_seconds": 463.7
}